sql_data_guard/__init__.py
sql_data_guard/restriction_validation.py
sql_data_guard/restriction_verification.py
sql_data_guard/sql_data_guard.py
sql_data_guard/verification_context.py
sql_data_guard/verification_utils.py
sql_data_guard/mcpwrapper/mcp_wrapper.py
sql_data_guard/rest/__init__.py
sql_data_guard/rest/sql_data_guard_rest.py
sql_data_guard-0.1.9.dist-info/licenses/LICENSE.md
sql_data_guard-0.1.9.dist-info/METADATA
sql_data_guard-0.1.9.dist-info/WHEEL
sql_data_guard-0.1.9.dist-info/top_level.txt
sql_data_guard-0.1.9.dist-info/RECORD
