Metadata-Version: 2.4
Name: sql-data-guard
Version: 0.1.9
Summary: Safety Layer for LLM Database Interactions
Author-email: Imperva - Threat Reseach Infra <ww.dis.imperva.threat-research-infra@thalesgroup.com>
License: MIT License
Project-URL: Homepage, https://github.com/ThalesGroup/sql-data-guard
Project-URL: Issues, https://github.com/ThalesGroup/sql-data-guard/issues
Classifier: Programming Language :: Python :: 3
Classifier: Operating System :: OS Independent
Requires-Python: >=3.8
License-File: LICENSE.md
Requires-Dist: sqlglot
Dynamic: license-file
